[
    {
        "kieu 1": [
            {
                "04": "Đà Nẵng",
                "quan": [
                    {
                        "01": "Hải Châu",
                        "phuong": [
                            {
                                "01": "Hòa Cường Bắc",
                                "kq": "04-01-01"
                            },
                            {
                                "02": "Hòa Cường Nam",
                                "kq": "04-01-02"
                            }
                        ]
                    },
                    {
                        "02": "Thanh Khê",
                        "phuong": [
                            {
                                "01": "Thuận Phước"
                            }
                        ]
                    }
                ]
            },
            {
                "01": "Hà Nội",
                "quan": []
            }
        ]
    },
    {
        "kieu2": [
            {
                "Đà Nẵng": [
                    {
                        "Hải Châu": [
                            {
                                "Hòa Cường Bắc": "04:01:01"
                            },
                            {
                                "Hòa Cường Nam": "04:01:02"
                            }
                        ]
                    },
                    {
                        "Thanh Khê": []
                    }
                ]
            },
            {
                "Hà Nội": []
            }
        ]
    }
]